azext_script/__init__.py
azext_script/_constants.py
azext_script/compilers/Compiler.py
azext_script/compilers/Handler.py
azext_script/compilers/HandlerManager.py
azext_script/compilers/__init__.py
azext_script/compilers/arm/__init__.py
azext_script/compilers/arm/handlers/Generic.py
azext_script/compilers/arm/handlers/ResourceGroup.py
azext_script/compilers/arm/handlers/Storage.py
azext_script/compilers/arm/handlers/__init__.py
azext_script/compilers/arm/transformer/ScriptTransformer.py
azext_script/compilers/arm/transformer/__init__.py
azext_script/compilers/az/__init__.py
azext_script/compilers/az/az_test.py
azext_script/compilers/az/handlers/ActiveDirectory.py
azext_script/compilers/az/handlers/AppInsights.py
azext_script/compilers/az/handlers/AppService.py
azext_script/compilers/az/handlers/CosmosDB.py
azext_script/compilers/az/handlers/Databricks.py
azext_script/compilers/az/handlers/EventGrid.py
azext_script/compilers/az/handlers/EventHubs.py
azext_script/compilers/az/handlers/Extension.py
azext_script/compilers/az/handlers/FunctionApp.py
azext_script/compilers/az/handlers/Generic.py
azext_script/compilers/az/handlers/HDInsight.py
azext_script/compilers/az/handlers/IoT.py
azext_script/compilers/az/handlers/ResourceGroup.py
azext_script/compilers/az/handlers/ServiceFabric.py
azext_script/compilers/az/handlers/SqlDb.py
azext_script/compilers/az/handlers/SqlServer.py
azext_script/compilers/az/handlers/Storage.py
azext_script/compilers/az/handlers/__init__.py
azext_script/compilers/az/handlers/simple-handlers/ResourceGroup.json
azext_script/compilers/az/handlers/simple-handlers/SimpleHandlers.json
azext_script/compilers/az/handlers/simple-handlers/SimpleHandlers.schema.json
azext_script/compilers/az/transformer/ScriptTransformer.py
azext_script/compilers/az/transformer/TranspilationResult.py
azext_script/compilers/az/transformer/__init__.py
azext_script/grammar/azsc.lark
azext_script/parser/__init__.py
azure_script-0.1.19.dist-info/DESCRIPTION.rst
azure_script-0.1.19.dist-info/METADATA
azure_script-0.1.19.dist-info/RECORD
azure_script-0.1.19.dist-info/WHEEL
azure_script-0.1.19.dist-info/metadata.json
azure_script-0.1.19.dist-info/top_level.txt
