Metadata-Version: 2.0
Name: azure-script
Version: 0.1.19
Summary: A script language to make deployment and management of Azure resources as simple and intelligent as possibile.
Home-page: https://github.com/yorek/azure-script
Author: Davide Mauri
Author-email: info@davidemauri.it
License: MIT
Platform: UNKNOWN
Classifier: Development Status :: 3 - Alpha
Classifier: Environment :: Console
Classifier: Operating System :: OS Independent
Classifier: Topic :: Internet
Classifier: Topic :: Software Development :: Code Generators
Classifier: Topic :: Software Development :: Interpreters
Classifier: Topic :: Utilities
Classifier: Intended Audience :: Developers
Classifier: Intended Audience :: System Administrators
Classifier: Programming Language :: Python
Classifier: Programming Language :: Python :: 2
Classifier: Programming Language :: Python :: 2.7
Classifier: Programming Language :: Python :: 3
Classifier: Programming Language :: Python :: 3.4
Classifier: Programming Language :: Python :: 3.5
Classifier: Programming Language :: Python :: 3.6
Classifier: License :: OSI Approved :: MIT License
Requires-Dist: lark-parser (==0.6.4)
